{
  "project_info": {
    "project_number": "368654862186",
    "project_id": "framy-app",
    "storage_bucket": "framy-app.firebasestorage.app"
  },
  "client": [
    {
      "client_info": {
        "mobilesdk_app_id": "1:368654862186:android:a4ecf49bce755af7f48713",
        "android_client_info": {
          "package_name": "com.example.mobile2project1"
        }
      },
      "oauth_client": [],
      "api_key": [
        {
          "current_key": "AIzaSyDF3_AygpnvYlAejVC-2Tv8DkcfZNbDvpk"
        }
      ],
      "services": {
        "appinvite_service": {
          "other_platform_oauth_client": []
        }
      }
    }
  ],
  "configuration_version": "1"
}